pyorganise/__init__.py
pyorganise/main.py
pyorganise-0.0.3.dist-info/LICENSE
pyorganise-0.0.3.dist-info/METADATA
pyorganise-0.0.3.dist-info/WHEEL
pyorganise-0.0.3.dist-info/top_level.txt
pyorganise-0.0.3.dist-info/RECORD
