Metadata-Version: 2.1
Name: pyorganise
Version: 0.0.3
Summary: A lightweight solution to organise your folders and files
Home-page: https://github.com/bat-fleck/pyOrganize
Author: Vishnu Prakash
Author-email: visheh10@gmail.com
License: UNKNOWN
Platform: UNKNOWN
Classifier: Programming Language :: Python :: 3
Classifier: License :: OSI Approved :: GNU General Public License v3 (GPLv3)
Classifier: Operating System :: OS Independent
Requires-Python: >=3.5
Requires-Dist: watchdog
